[
    {
        "id": "ChIJb14VxPSaP44Rct31HesfJ-k",
        "name": "Gimnasio Smart Fit - Calle 85 Cabrera",
        "address": "Ac. 85 ##14-5, Bogot\u00e1, Colombia",
        "types": [
            "gym",
            "health",
            "point_of_interest",
            "establishment"
        ],
        "coordinates": {
            "lat": 4.6696049,
            "lng": -74.05466330000002
        },
        "rating": 4.5,
        "rating_n": 432,
        "international_phone_number": "+57 350 3100919",
        "current_popularity": 29,
        "populartimes": [
            {
                "name": "Monday",
                "data": [
                    0,
                    0,
                    0,
                    0,
                    0,
                    13,
                    30,
                    44,
                    48,
                    44,
                    37,
                    34,
                    30,
                    24,
                    17,
                    18,
                    35,
                    64,
                    86,
                    80,
                    51,
                    19,
                    0,
                    0
                ]
            },
            {
                "name": "Tuesday",
                "data": [
                    0,
                    0,
                    0,
                    0,
                    0,
                    19,
                    31,
                    42,
                    51,
                    55,
                    52,
                    44,
                    33,
                    22,
                    15,
                    20,
                    41,
                    75,
                    100,
                    93,
                    60,
                    24,
                    0,
                    0
                ]
            },
            {
                "name": "Wednesday",
                "data": [
                    0,
                    0,
                    0,
                    0,
                    0,
                    24,
                    43,
                    52,
                    49,
                    40,
                    35,
                    36,
                    34,
                    29,
                    25,
                    32,
                    49,
                    69,
                    80,
                    76,
                    58,
                    34,
                    0,
                    0
                ]
            },
            {
                "name": "Thursday",
                "data": [
                    0,
                    0,
                    0,
                    0,
                    0,
                    22,
                    34,
                    46,
                    52,
                    51,
                    45,
                    34,
                    23,
                    16,
                    16,
                    25,
                    44,
                    66,
                    78,
                    72,
                    52,
                    28,
                    0,
                    0
                ]
            },
            {
                "name": "Friday",
                "data": [
                    0,
                    0,
                    0,
                    0,
                    0,
                    21,
                    32,
                    40,
                    45,
                    45,
                    40,
                    32,
                    24,
                    19,
                    20,
                    28,
                    41,
                    52,
                    56,
                    50,
                    36,
                    0,
                    0,
                    0
                ]
            },
            {
                "name": "Saturday",
                "data": [
                    0,
                    0,
                    0,
                    0,
                    0,
                    0,
                    0,
                    16,
                    19,
                    22,
                    23,
                    24,
                    23,
                    20,
                    17,
                    14,
                    10,
                    0,
                    0,
                    0,
                    0,
                    0,
                    0,
                    0
                ]
            },
            {
                "name": "Sunday",
                "data": [
                    0,
                    0,
                    0,
                    0,
                    0,
                    0,
                    0,
                    0,
                    3,
                    7,
                    10,
                    12,
                    12,
                    10,
                    7,
                    3,
                    1,
                    0,
                    0,
                    0,
                    0,
                    0,
                    0,
                    0
                ]
            }
        ],
        "time_spent": [
            45,
            120
        ]
    },
    {
        "id": "ChIJNaZt_NabP44RyEgxYmwYufQ",
        "name": "Bodytech Calle 90",
        "address": "Cl. 90 ###16-30, Bogot\u00e1, Colombia",
        "types": [
            "gym",
            "health",
            "point_of_interest",
            "establishment"
        ],
        "coordinates": {
            "lat": 4.675184799999999,
            "lng": -74.0541563
        },
        "rating": 4.6,
        "rating_n": 193,
        "international_phone_number": "+57 601 7422639",
        "current_popularity": 36,
        "populartimes": [
            {
                "name": "Monday",
                "data": [
                    0,
                    0,
                    0,
                    0,
                    4,
                    20,
                    42,
                    59,
                    63,
                    55,
                    49,
                    52,
                    57,
                    57,
                    53,
                    50,
                    58,
                    72,
                    83,
                    81,
                    64,
                    41,
                    19,
                    4
                ]
            },
            {
                "name": "Tuesday",
                "data": [
                    0,
                    0,
                    0,
                    0,
                    6,
                    28,
                    60,
                    86,
                    92,
                    77,
                    59,
                    53,
                    60,
                    72,
                    79,
                    81,
                    83,
                    88,
                    92,
                    87,
                    70,
                    46,
                    23,
                    6
                ]
            },
            {
                "name": "Wednesday",
                "data": [
                    0,
                    0,
                    0,
                    0,
                    3,
                    22,
                    51,
                    77,
                    86,
                    77,
                    64,
                    59,
                    60,
                    62,
                    61,
                    62,
                    68,
                    80,
                    88,
                    84,
                    68,
                    45,
                    22,
                    6
                ]
            },
            {
                "name": "Thursday",
                "data": [
                    0,
                    0,
                    0,
                    0,
                    3,
                    21,
                    48,
                    76,
                    90,
                    85,
                    70,
                    59,
                    57,
                    63,
                    71,
                    76,
                    80,
                    82,
                    82,
                    78,
                    69,
                    55,
                    37,
                    21
                ]
            },
            {
                "name": "Friday",
                "data": [
                    0,
                    0,
                    0,
                    0,
                    8,
                    28,
                    57,
                    80,
                    86,
                    78,
                    67,
                    65,
                    70,
                    75,
                    76,
                    75,
                    78,
                    87,
                    97,
                    100,
                    89,
                    67,
                    0,
                    0
                ]
            },
            {
                "name": "Saturday",
                "data": [
                    0,
                    0,
                    0,
                    0,
                    0,
                    0,
                    21,
                    39,
                    59,
                    77,
                    88,
                    90,
                    82,
                    71,
                    60,
                    54,
                    53,
                    54,
                    55,
                    55,
                    0,
                    0,
                    0,
                    0
                ]
            },
            {
                "name": "Sunday",
                "data": [
                    0,
                    0,
                    0,
                    0,
                    0,
                    0,
                    6,
                    15,
                    25,
                    35,
                    44,
                    48,
                    48,
                    48,
                    48,
                    50,
                    49,
                    42,
                    0,
                    0,
                    0,
                    0,
                    0,
                    0
                ]
            }
        ]
    },
    {
        "id": "ChIJecViMZKaP44RbtXTAbRrjuo",
        "name": "Fit for all",
        "address": "Cl. 94 ## 13 - 11, Bogot\u00e1, Cundinamarca, Colombia",
        "types": [
            "gym",
            "health",
            "point_of_interest",
            "establishment"
        ],
        "coordinates": {
            "lat": 4.678236099999999,
            "lng": -74.0486917
        },
        "rating": 4.5,
        "rating_n": 246,
        "international_phone_number": "+57 310 4788982",
        "current_popularity": 15,
        "populartimes": [
            {
                "name": "Monday",
                "data": [
                    0,
                    0,
                    0,
                    0,
                    0,
                    14,
                    31,
                    42,
                    40,
                    32,
                    28,
                    30,
                    34,
                    37,
                    42,
                    52,
                    68,
                    82,
                    82,
                    66,
                    41,
                    17,
                    0,
                    0
                ]
            },
            {
                "name": "Tuesday",
                "data": [
                    0,
                    0,
                    0,
                    0,
                    0,
                    24,
                    52,
                    70,
                    64,
                    45,
                    31,
                    28,
                    28,
                    24,
                    21,
                    27,
                    52,
                    85,
                    100,
                    79,
                    41,
                    11,
                    0,
                    0
                ]
            },
            {
                "name": "Wednesday",
                "data": [
                    0,
                    0,
                    0,
                    0,
                    0,
                    29,
                    62,
                    57,
                    36,
                    30,
                    31,
                    31,
                    27,
                    23,
                    24,
                    36,
                    58,
                    80,
                    88,
                    75,
                    48,
                    21,
                    0,
                    0
                ]
            },
            {
                "name": "Thursday",
                "data": [
                    0,
                    0,
                    0,
                    0,
                    0,
                    14,
                    41,
                    62,
                    63,
                    48,
                    38,
                    37,
                    36,
                    32,
                    27,
                    30,
                    42,
                    57,
                    64,
                    56,
                    38,
                    18,
                    0,
                    0
                ]
            },
            {
                "name": "Friday",
                "data": [
                    0,
                    0,
                    0,
                    0,
                    0,
                    13,
                    32,
                    44,
                    43,
                    35,
                    29,
                    25,
                    22,
                    19,
                    18,
                    21,
                    28,
                    36,
                    39,
                    36,
                    27,
                    17,
                    0,
                    0
                ]
            },
            {
                "name": "Saturday",
                "data": [
                    0,
                    0,
                    0,
                    0,
                    0,
                    0,
                    1,
                    13,
                    28,
                    38,
                    38,
                    32,
                    25,
                    23,
                    21,
                    19,
                    14,
                    0,
                    0,
                    0,
                    0,
                    0,
                    0,
                    0
                ]
            },
            {
                "name": "Sunday",
                "data": [
                    0,
                    0,
                    0,
                    0,
                    0,
                    0,
                    0,
                    1,
                    9,
                    16,
                    17,
                    15,
                    13,
                    11,
                    10,
                    8,
                    4,
                    0,
                    0,
                    0,
                    0,
                    0,
                    0,
                    0
                ]
            }
        ]
    },
    {
        "id": "ChIJGwuMKaubP44R-xFCut5CCvc",
        "name": "Athletic gym HUB 72",
        "address": "Cra. 26 ##71b-30, Bogot\u00e1, Colombia",
        "types": [
            "gym",
            "health",
            "point_of_interest",
            "establishment"
        ],
        "coordinates": {
            "lat": 4.662480299999999,
            "lng": -74.0676859
        },
        "rating": 4.6,
        "rating_n": 418,
        "international_phone_number": "+57 310 2328482",
        "current_popularity": 13,
        "populartimes": [
            {
                "name": "Monday",
                "data": [
                    0,
                    0,
                    0,
                    0,
                    0,
                    24,
                    41,
                    49,
                    44,
                    33,
                    26,
                    26,
                    28,
                    26,
                    22,
                    21,
                    33,
                    60,
                    87,
                    91,
                    67,
                    34,
                    0,
                    0
                ]
            },
            {
                "name": "Tuesday",
                "data": [
                    0,
                    0,
                    0,
                    0,
                    0,
                    35,
                    59,
                    68,
                    58,
                    40,
                    30,
                    29,
                    30,
                    28,
                    23,
                    22,
                    35,
                    65,
                    95,
                    100,
                    73,
                    37,
                    0,
                    0
                ]
            },
            {
                "name": "Wednesday",
                "data": [
                    0,
                    0,
                    0,
                    0,
                    0,
                    34,
                    63,
                    75,
                    63,
                    41,
                    29,
                    30,
                    31,
                    27,
                    21,
                    21,
                    35,
                    63,
                    87,
                    89,
                    66,
                    35,
                    0,
                    0
                ]
            },
            {
                "name": "Thursday",
                "data": [
                    0,
                    0,
                    0,
                    0,
                    0,
                    30,
                    57,
                    67,
                    53,
                    35,
                    29,
                    31,
                    31,
                    26,
                    20,
                    20,
                    34,
                    58,
                    79,
                    80,
                    59,
                    31,
                    0,
                    0
                ]
            },
            {
                "name": "Friday",
                "data": [
                    0,
                    0,
                    0,
                    0,
                    0,
                    25,
                    51,
                    58,
                    44,
                    33,
                    31,
                    30,
                    27,
                    23,
                    17,
                    15,
                    22,
                    40,
                    59,
                    59,
                    37,
                    0,
                    0,
                    0
                ]
            },
            {
                "name": "Saturday",
                "data": [
                    0,
                    0,
                    0,
                    0,
                    0,
                    0,
                    15,
                    27,
                    35,
                    37,
                    35,
                    31,
                    29,
                    27,
                    25,
                    21,
                    16,
                    11,
                    0,
                    0,
                    0,
                    0,
                    0,
                    0
                ]
            },
            {
                "name": "Sunday",
                "data": [
                    0,
                    0,
                    0,
                    0,
                    0,
                    0,
                    0,
                    7,
                    16,
                    25,
                    30,
                    28,
                    23,
                    20,
                    17,
                    13,
                    6,
                    0,
                    0,
                    0,
                    0,
                    0,
                    0,
                    0
                ]
            }
        ],
        "time_spent": [
            60,
            120
        ]
    },
    {
        "id": "ChIJeTIGh5aaP44RONASHAYkKKg",
        "name": "Spinning Center GYM",
        "address": "Cra. 13 ## 93A - 45, Bogot\u00e1, Cundinamarca, Colombia",
        "types": [
            "gym",
            "health",
            "point_of_interest",
            "establishment"
        ],
        "coordinates": {
            "lat": 4.6774377,
            "lng": -74.04917139999999
        },
        "rating": 4.5,
        "rating_n": 113,
        "international_phone_number": "+57 318 5170441",
        "populartimes": [
            {
                "name": "Monday",
                "data": [
                    0,
                    0,
                    0,
                    0,
                    0,
                    19,
                    42,
                    61,
                    62,
                    48,
                    38,
                    40,
                    45,
                    44,
                    36,
                    34,
                    51,
                    82,
                    100,
                    83,
                    46,
                    15,
                    0,
                    0
                ]
            },
            {
                "name": "Tuesday",
                "data": [
                    0,
                    0,
                    0,
                    0,
                    0,
                    18,
                    42,
                    62,
                    63,
                    49,
                    39,
                    39,
                    43,
                    43,
                    40,
                    43,
                    60,
                    84,
                    93,
                    74,
                    41,
                    15,
                    0,
                    0
                ]
            },
            {
                "name": "Wednesday",
                "data": [
                    0,
                    0,
                    0,
                    0,
                    0,
                    19,
                    47,
                    70,
                    68,
                    50,
                    42,
                    47,
                    51,
                    43,
                    32,
                    30,
                    47,
                    76,
                    94,
                    87,
                    59,
                    28,
                    0,
                    0
                ]
            },
            {
                "name": "Thursday",
                "data": [
                    0,
                    0,
                    0,
                    0,
                    0,
                    19,
                    42,
                    62,
                    63,
                    49,
                    38,
                    36,
                    39,
                    40,
                    38,
                    39,
                    50,
                    65,
                    74,
                    64,
                    41,
                    19,
                    0,
                    0
                ]
            },
            {
                "name": "Friday",
                "data": [
                    0,
                    0,
                    0,
                    0,
                    0,
                    11,
                    28,
                    44,
                    51,
                    47,
                    42,
                    42,
                    44,
                    42,
                    37,
                    36,
                    39,
                    43,
                    41,
                    32,
                    20,
                    0,
                    0,
                    0
                ]
            },
            {
                "name": "Saturday",
                "data": [
                    0,
                    0,
                    0,
                    0,
                    0,
                    0,
                    0,
                    15,
                    31,
                    48,
                    56,
                    52,
                    42,
                    36,
                    34,
                    31,
                    22,
                    12,
                    0,
                    0,
                    0,
                    0,
                    0,
                    0
                ]
            },
            {
                "name": "Sunday",
                "data": [
                    0,
                    0,
                    0,
                    0,
                    0,
                    0,
                    0,
                    3,
                    11,
                    23,
                    32,
                    31,
                    24,
                    16,
                    12,
                    11,
                    0,
                    0,
                    0,
                    0,
                    0,
                    0,
                    0,
                    0
                ]
            }
        ],
        "time_spent": [
            60,
            120
        ]
    },
    {
        "id": "ChIJrTBBJz2bP44R2mrE05rC0l4",
        "name": "Gimnasio",
        "address": "Cra. 26 ##71b-30, Bogot\u00e1, Colombia",
        "types": [
            "gym",
            "health",
            "point_of_interest",
            "establishment"
        ],
        "coordinates": {
            "lat": 4.6634506,
            "lng": -74.0680406
        },
        "rating": 4.6,
        "rating_n": 418,
        "current_popularity": 13,
        "populartimes": [
            {
                "name": "Monday",
                "data": [
                    0,
                    0,
                    0,
                    0,
                    0,
                    24,
                    41,
                    49,
                    44,
                    33,
                    26,
                    26,
                    28,
                    26,
                    22,
                    21,
                    33,
                    60,
                    87,
                    91,
                    67,
                    34,
                    0,
                    0
                ]
            },
            {
                "name": "Tuesday",
                "data": [
                    0,
                    0,
                    0,
                    0,
                    0,
                    35,
                    59,
                    68,
                    58,
                    40,
                    30,
                    29,
                    30,
                    28,
                    23,
                    22,
                    35,
                    65,
                    95,
                    100,
                    73,
                    37,
                    0,
                    0
                ]
            },
            {
                "name": "Wednesday",
                "data": [
                    0,
                    0,
                    0,
                    0,
                    0,
                    34,
                    63,
                    75,
                    63,
                    41,
                    29,
                    30,
                    31,
                    27,
                    21,
                    21,
                    35,
                    63,
                    87,
                    89,
                    66,
                    35,
                    0,
                    0
                ]
            },
            {
                "name": "Thursday",
                "data": [
                    0,
                    0,
                    0,
                    0,
                    0,
                    30,
                    57,
                    67,
                    53,
                    35,
                    29,
                    31,
                    31,
                    26,
                    20,
                    20,
                    34,
                    58,
                    79,
                    80,
                    59,
                    31,
                    0,
                    0
                ]
            },
            {
                "name": "Friday",
                "data": [
                    0,
                    0,
                    0,
                    0,
                    0,
                    25,
                    51,
                    58,
                    44,
                    33,
                    31,
                    30,
                    27,
                    23,
                    17,
                    15,
                    22,
                    40,
                    59,
                    59,
                    37,
                    0,
                    0,
                    0
                ]
            },
            {
                "name": "Saturday",
                "data": [
                    0,
                    0,
                    0,
                    0,
                    0,
                    0,
                    15,
                    27,
                    35,
                    37,
                    35,
                    31,
                    29,
                    27,
                    25,
                    21,
                    16,
                    11,
                    0,
                    0,
                    0,
                    0,
                    0,
                    0
                ]
            },
            {
                "name": "Sunday",
                "data": [
                    0,
                    0,
                    0,
                    0,
                    0,
                    0,
                    0,
                    7,
                    16,
                    25,
                    30,
                    28,
                    23,
                    20,
                    17,
                    13,
                    6,
                    0,
                    0,
                    0,
                    0,
                    0,
                    0,
                    0
                ]
            }
        ],
        "time_spent": [
            60,
            120
        ]
    },
    {
        "id": "ChIJG5ckofaaP44Rwb-0qf0sZRk",
        "name": "Elena del Mar",
        "address": "Ak. 20 #82-57, Bogot\u00e1, Colombia",
        "types": [
            "gym",
            "health",
            "point_of_interest",
            "establishment"
        ],
        "coordinates": {
            "lat": 4.670296399999999,
            "lng": -74.060559
        },
        "rating": 4.1,
        "rating_n": 66
    },
    {
        "id": "ChIJ-7Q8Y_maP44RZeXvasVAqfQ",
        "name": "POWER TRAINER GYM",
        "address": "Cl. 78 #29B-36B, Barrios Unidos, Bogot\u00e1, Colombia",
        "types": [
            "gym",
            "health",
            "point_of_interest",
            "establishment"
        ],
        "coordinates": {
            "lat": 4.6703872,
            "lng": -74.0702993
        },
        "rating": 4.7,
        "rating_n": 46,
        "international_phone_number": "+57 311 2802639",
        "populartimes": [
            {
                "name": "Monday",
                "data": [
                    0,
                    0,
                    0,
                    0,
                    0,
                    10,
                    16,
                    25,
                    32,
                    34,
                    31,
                    25,
                    0,
                    0,
                    0,
                    20,
                    26,
                    57,
                    100,
                    86,
                    37,
                    12,
                    0,
                    0
                ]
            },
            {
                "name": "Tuesday",
                "data": [
                    0,
                    0,
                    0,
                    0,
                    0,
                    15,
                    20,
                    23,
                    26,
                    26,
                    25,
                    22,
                    0,
                    0,
                    0,
                    16,
                    31,
                    56,
                    76,
                    77,
                    57,
                    32,
                    0,
                    0
                ]
            },
            {
                "name": "Wednesday",
                "data": [
                    0,
                    0,
                    0,
                    0,
                    0,
                    13,
                    20,
                    26,
                    30,
                    29,
                    24,
                    20,
                    0,
                    0,
                    0,
                    17,
                    31,
                    53,
                    77,
                    83,
                    64,
                    37,
                    0,
                    0
                ]
            },
            {
                "name": "Thursday",
                "data": [
                    0,
                    0,
                    0,
                    0,
                    0,
                    12,
                    20,
                    30,
                    38,
                    42,
                    42,
                    37,
                    0,
                    0,
                    0,
                    11,
                    24,
                    59,
                    94,
                    91,
                    52,
                    19,
                    0,
                    0
                ]
            },
            {
                "name": "Friday",
                "data": [
                    0,
                    0,
                    0,
                    0,
                    0,
                    8,
                    15,
                    23,
                    30,
                    33,
                    31,
                    25,
                    0,
                    0,
                    0,
                    29,
                    46,
                    66,
                    79,
                    82,
                    70,
                    51,
                    0,
                    0
                ]
            },
            {
                "name": "Saturday",
                "data": [
                    0,
                    0,
                    0,
                    0,
                    0,
                    0,
                    0,
                    0,
                    0,
                    0,
                    0,
                    0,
                    0,
                    0,
                    0,
                    0,
                    0,
                    0,
                    0,
                    0,
                    0,
                    0,
                    0,
                    0
                ]
            },
            {
                "name": "Sunday",
                "data": [
                    0,
                    0,
                    0,
                    0,
                    0,
                    0,
                    0,
                    0,
                    0,
                    0,
                    0,
                    0,
                    0,
                    0,
                    0,
                    0,
                    0,
                    0,
                    0,
                    0,
                    0,
                    0,
                    0,
                    0
                ]
            }
        ]
    },
    {
        "id": "ChIJwX0siVyaP44RYWJr7dUbzqU",
        "name": "Gimnasio Bloque C 107",
        "address": "Cl. 72 #11-86, Localidad de Chapinero, Bogot\u00e1, Colombia",
        "types": [
            "gym",
            "health",
            "point_of_interest",
            "establishment"
        ],
        "coordinates": {
            "lat": 4.658365399999999,
            "lng": -74.0591799
        },
        "rating": 3,
        "rating_n": 2,
        "international_phone_number": "+57 601 5941894"
    },
    {
        "id": "ChIJeW2q4pCaP44RA-o62wRa54A",
        "name": "Bodytech Cra 11",
        "address": "Cl. 96 ##10-38, Bogot\u00e1, Colombia",
        "types": [
            "gym",
            "health",
            "point_of_interest",
            "establishment"
        ],
        "coordinates": {
            "lat": 4.6791369,
            "lng": -74.04467679999999
        },
        "rating": 4.7,
        "rating_n": 160,
        "international_phone_number": "+57 601 7422639",
        "current_popularity": 50,
        "populartimes": [
            {
                "name": "Monday",
                "data": [
                    0,
                    0,
                    0,
                    0,
                    24,
                    46,
                    67,
                    80,
                    83,
                    79,
                    70,
                    61,
                    55,
                    51,
                    51,
                    53,
                    59,
                    66,
                    71,
                    70,
                    62,
                    48,
                    29,
                    11
                ]
            },
            {
                "name": "Tuesday",
                "data": [
                    0,
                    0,
                    0,
                    0,
                    32,
                    55,
                    77,
                    92,
                    100,
                    97,
                    87,
                    74,
                    64,
                    60,
                    63,
                    71,
                    78,
                    82,
                    80,
                    69,
                    54,
                    35,
                    17,
                    2
                ]
            },
            {
                "name": "Wednesday",
                "data": [
                    0,
                    0,
                    0,
                    0,
                    41,
                    65,
                    82,
                    88,
                    85,
                    80,
                    77,
                    76,
                    75,
                    71,
                    65,
                    61,
                    61,
                    65,
                    68,
                    66,
                    55,
                    39,
                    19,
                    2
                ]
            },
            {
                "name": "Thursday",
                "data": [
                    0,
                    0,
                    0,
                    0,
                    22,
                    40,
                    58,
                    73,
                    83,
                    87,
                    85,
                    78,
                    70,
                    64,
                    63,
                    69,
                    79,
                    88,
                    93,
                    89,
                    76,
                    55,
                    33,
                    13
                ]
            },
            {
                "name": "Friday",
                "data": [
                    0,
                    0,
                    0,
                    0,
                    13,
                    36,
                    56,
                    69,
                    72,
                    69,
                    65,
                    61,
                    58,
                    51,
                    45,
                    41,
                    42,
                    45,
                    47,
                    44,
                    35,
                    21,
                    0,
                    0
                ]
            },
            {
                "name": "Saturday",
                "data": [
                    0,
                    0,
                    0,
                    0,
                    0,
                    0,
                    9,
                    20,
                    32,
                    42,
                    47,
                    45,
                    39,
                    30,
                    23,
                    19,
                    19,
                    20,
                    19,
                    15,
                    0,
                    0,
                    0,
                    0
                ]
            },
            {
                "name": "Sunday",
                "data": [
                    0,
                    0,
                    0,
                    0,
                    0,
                    0,
                    6,
                    12,
                    18,
                    24,
                    28,
                    30,
                    31,
                    29,
                    25,
                    19,
                    13,
                    8,
                    0,
                    0,
                    0,
                    0,
                    0,
                    0
                ]
            }
        ],
        "time_spent": [
            45,
            150
        ]
    },
    {
        "id": "ChIJoVlbWIuaP44RDol6k7hAbJM",
        "name": "CrossFit Bogot\u00e1",
        "address": "Cra. 13 ## 86a-51, Bogot\u00e1, Cundinamarca, Colombia",
        "types": [
            "gym",
            "health",
            "point_of_interest",
            "establishment"
        ],
        "coordinates": {
            "lat": 4.670965699999999,
            "lng": -74.0526273
        },
        "rating": 4.7,
        "rating_n": 84,
        "international_phone_number": "+57 315 4291484",
        "populartimes": [
            {
                "name": "Monday",
                "data": [
                    0,
                    0,
                    0,
                    0,
                    0,
                    0,
                    22,
                    30,
                    36,
                    39,
                    40,
                    39,
                    36,
                    35,
                    39,
                    49,
                    61,
                    67,
                    61,
                    44,
                    0,
                    0,
                    0,
                    0
                ]
            },
            {
                "name": "Tuesday",
                "data": [
                    0,
                    0,
                    0,
                    0,
                    0,
                    0,
                    18,
                    39,
                    53,
                    55,
                    46,
                    32,
                    23,
                    27,
                    43,
                    67,
                    87,
                    100,
                    97,
                    82,
                    0,
                    0,
                    0,
                    0
                ]
            },
            {
                "name": "Wednesday",
                "data": [
                    0,
                    0,
                    0,
                    0,
                    0,
                    0,
                    26,
                    45,
                    60,
                    67,
                    63,
                    54,
                    45,
                    40,
                    42,
                    49,
                    58,
                    65,
                    65,
                    58,
                    0,
                    0,
                    0,
                    0
                ]
            },
            {
                "name": "Thursday",
                "data": [
                    0,
                    0,
                    0,
                    0,
                    0,
                    0,
                    20,
                    47,
                    64,
                    68,
                    62,
                    56,
                    54,
                    53,
                    53,
                    55,
                    59,
                    63,
                    65,
                    63,
                    0,
                    0,
                    0,
                    0
                ]
            },
            {
                "name": "Friday",
                "data": [
                    0,
                    0,
                    0,
                    0,
                    0,
                    0,
                    13,
                    38,
                    57,
                    63,
                    60,
                    54,
                    51,
                    49,
                    48,
                    47,
                    48,
                    50,
                    52,
                    54,
                    0,
                    0,
                    0,
                    0
                ]
            },
            {
                "name": "Saturday",
                "data": [
                    0,
                    0,
                    0,
                    0,
                    0,
                    0,
                    0,
                    0,
                    0,
                    54,
                    59,
                    41,
                    0,
                    0,
                    0,
                    0,
                    0,
                    0,
                    0,
                    0,
                    0,
                    0,
                    0,
                    0
                ]
            },
            {
                "name": "Sunday",
                "data": [
                    0,
                    0,
                    0,
                    0,
                    0,
                    0,
                    0,
                    0,
                    0,
                    0,
                    0,
                    0,
                    0,
                    0,
                    0,
                    0,
                    0,
                    0,
                    0,
                    0,
                    0,
                    0,
                    0,
                    0
                ]
            }
        ]
    },
    {
        "id": "ChIJ8xhBmF6bP44RD9Mxd0aTKqM",
        "name": "Gimnasio Body Sport",
        "address": "entre la 52 y la 36, Calle 68 # 52 36 san fernado, Bogot\u00e1, Colombia",
        "types": [
            "gym",
            "health",
            "point_of_interest",
            "establishment"
        ],
        "coordinates": {
            "lat": 4.664928199999999,
            "lng": -74.0756178
        },
        "rating": 4.3,
        "rating_n": 60,
        "international_phone_number": "+57 310 2867827"
    },
    {
        "id": "ChIJO1k8cxObP44Ry-uUv2T8mOU",
        "name": "Gimnasio Compensar Calle 94",
        "address": "Cl. 94 #43 N \u00b0 23, Bogot\u00e1, Colombia",
        "types": [
            "gym",
            "health",
            "point_of_interest",
            "establishment"
        ],
        "coordinates": {
            "lat": 4.6811826,
            "lng": -74.05750080000001
        },
        "rating": 4.5,
        "rating_n": 1271,
        "populartimes": [
            {
                "name": "Monday",
                "data": [
                    0,
                    0,
                    0,
                    0,
                    0,
                    0,
                    48,
                    85,
                    86,
                    81,
                    87,
                    75,
                    53,
                    45,
                    52,
                    59,
                    57,
                    46,
                    31,
                    0,
                    0,
                    0,
                    0,
                    0
                ]
            },
            {
                "name": "Tuesday",
                "data": [
                    0,
                    0,
                    0,
                    0,
                    0,
                    0,
                    55,
                    91,
                    88,
                    76,
                    77,
                    73,
                    60,
                    53,
                    55,
                    59,
                    56,
                    46,
                    32,
                    0,
                    0,
                    0,
                    0,
                    0
                ]
            },
            {
                "name": "Wednesday",
                "data": [
                    0,
                    0,
                    0,
                    0,
                    0,
                    0,
                    61,
                    100,
                    98,
                    89,
                    84,
                    72,
                    60,
                    57,
                    61,
                    63,
                    58,
                    46,
                    30,
                    0,
                    0,
                    0,
                    0,
                    0
                ]
            },
            {
                "name": "Thursday",
                "data": [
                    0,
                    0,
                    0,
                    0,
                    0,
                    0,
                    57,
                    92,
                    95,
                    85,
                    83,
                    78,
                    64,
                    52,
                    50,
                    49,
                    45,
                    36,
                    24,
                    0,
                    0,
                    0,
                    0,
                    0
                ]
            },
            {
                "name": "Friday",
                "data": [
                    0,
                    0,
                    0,
                    0,
                    0,
                    0,
                    61,
                    94,
                    93,
                    81,
                    75,
                    65,
                    55,
                    48,
                    48,
                    47,
                    43,
                    33,
                    22,
                    0,
                    0,
                    0,
                    0,
                    0
                ]
            },
            {
                "name": "Saturday",
                "data": [
                    0,
                    0,
                    0,
                    0,
                    0,
                    0,
                    54,
                    90,
                    97,
                    88,
                    74,
                    56,
                    41,
                    31,
                    24,
                    16,
                    10,
                    5,
                    1,
                    0,
                    0,
                    0,
                    0,
                    0
                ]
            },
            {
                "name": "Sunday",
                "data": [
                    0,
                    0,
                    0,
                    0,
                    0,
                    0,
                    0,
                    38,
                    62,
                    60,
                    43,
                    35,
                    28,
                    18,
                    8,
                    2,
                    0,
                    0,
                    0,
                    0,
                    0,
                    0,
                    0,
                    0
                ]
            }
        ],
        "time_spent": [
            45,
            90
        ]
    },
    {
        "id": "ChIJyYaK-GGaP44RVFyji846674",
        "name": "Bodytech Cabrera",
        "address": "Ac. 85 #7-13, Bogot\u00e1, Cundinamarca, Colombia",
        "types": [
            "gym",
            "health",
            "point_of_interest",
            "establishment"
        ],
        "coordinates": {
            "lat": 4.6650848,
            "lng": -74.04721649999999
        },
        "rating": 4.4,
        "rating_n": 193,
        "international_phone_number": "+57 1 800 0182639",
        "current_popularity": 15,
        "populartimes": [
            {
                "name": "Monday",
                "data": [
                    0,
                    0,
                    0,
                    0,
                    10,
                    33,
                    62,
                    81,
                    80,
                    70,
                    69,
                    76,
                    78,
                    70,
                    59,
                    54,
                    56,
                    62,
                    63,
                    57,
                    46,
                    31,
                    17,
                    7
                ]
            },
            {
                "name": "Tuesday",
                "data": [
                    0,
                    0,
                    0,
                    0,
                    14,
                    37,
                    62,
                    77,
                    78,
                    77,
                    84,
                    95,
                    98,
                    89,
                    75,
                    66,
                    65,
                    67,
                    66,
                    57,
                    42,
                    25,
                    12,
                    2
                ]
            },
            {
                "name": "Wednesday",
                "data": [
                    0,
                    0,
                    0,
                    0,
                    12,
                    33,
                    61,
                    82,
                    89,
                    87,
                    87,
                    90,
                    90,
                    82,
                    71,
                    67,
                    70,
                    76,
                    77,
                    68,
                    52,
                    34,
                    17,
                    6
                ]
            },
            {
                "name": "Thursday",
                "data": [
                    0,
                    0,
                    0,
                    0,
                    16,
                    30,
                    48,
                    66,
                    84,
                    96,
                    100,
                    95,
                    85,
                    72,
                    62,
                    56,
                    57,
                    63,
                    68,
                    68,
                    57,
                    39,
                    21,
                    8
                ]
            },
            {
                "name": "Friday",
                "data": [
                    0,
                    0,
                    0,
                    0,
                    8,
                    27,
                    53,
                    77,
                    86,
                    83,
                    80,
                    85,
                    89,
                    82,
                    67,
                    55,
                    52,
                    56,
                    58,
                    56,
                    48,
                    36,
                    0,
                    0
                ]
            },
            {
                "name": "Saturday",
                "data": [
                    0,
                    0,
                    0,
                    0,
                    0,
                    0,
                    24,
                    40,
                    58,
                    74,
                    83,
                    83,
                    77,
                    67,
                    57,
                    49,
                    44,
                    40,
                    37,
                    33,
                    0,
                    0,
                    0,
                    0
                ]
            },
            {
                "name": "Sunday",
                "data": [
                    0,
                    0,
                    0,
                    0,
                    0,
                    0,
                    14,
                    22,
                    31,
                    40,
                    45,
                    47,
                    44,
                    38,
                    32,
                    27,
                    24,
                    21,
                    0,
                    0,
                    0,
                    0,
                    0,
                    0
                ]
            }
        ],
        "time_spent": [
            15,
            15
        ]
    },
    {
        "id": "ChIJYxCs4eKaP44RK1IYGm3ZaHI",
        "name": "Gimnasio",
        "address": "Cra. 58 #79b-52, Bogot\u00e1, Colombia",
        "types": [
            "gym",
            "health",
            "point_of_interest",
            "establishment"
        ],
        "coordinates": {
            "lat": 4.6779663,
            "lng": -74.074268
        },
        "rating": 4.6,
        "rating_n": 45
    },
    {
        "id": "ChIJPykSSkGaP44Ryie81YIlTl0",
        "name": "stark smart gym",
        "address": "Cl. 66 ##7-28 Piso 5, Bogot\u00e1, Colombia",
        "types": [
            "gym",
            "health",
            "point_of_interest",
            "establishment"
        ],
        "coordinates": {
            "lat": 4.65006,
            "lng": -74.0590314
        },
        "rating": 4.5,
        "rating_n": 419,
        "current_popularity": 11,
        "populartimes": [
            {
                "name": "Monday",
                "data": [
                    0,
                    0,
                    0,
                    0,
                    0,
                    27,
                    37,
                    43,
                    42,
                    37,
                    32,
                    29,
                    28,
                    27,
                    26,
                    29,
                    41,
                    62,
                    79,
                    77,
                    55,
                    28,
                    0,
                    0
                ]
            },
            {
                "name": "Tuesday",
                "data": [
                    0,
                    0,
                    0,
                    0,
                    0,
                    33,
                    50,
                    55,
                    47,
                    36,
                    33,
                    38,
                    37,
                    26,
                    17,
                    23,
                    49,
                    82,
                    100,
                    87,
                    55,
                    24,
                    0,
                    0
                ]
            },
            {
                "name": "Wednesday",
                "data": [
                    0,
                    0,
                    0,
                    0,
                    0,
                    35,
                    69,
                    80,
                    60,
                    39,
                    35,
                    39,
                    40,
                    34,
                    30,
                    37,
                    55,
                    76,
                    86,
                    78,
                    55,
                    30,
                    0,
                    0
                ]
            },
            {
                "name": "Thursday",
                "data": [
                    0,
                    0,
                    0,
                    0,
                    0,
                    31,
                    52,
                    62,
                    53,
                    38,
                    30,
                    30,
                    30,
                    25,
                    21,
                    25,
                    43,
                    68,
                    82,
                    75,
                    50,
                    24,
                    0,
                    0
                ]
            },
            {
                "name": "Friday",
                "data": [
                    0,
                    0,
                    0,
                    0,
                    0,
                    20,
                    41,
                    55,
                    54,
                    42,
                    35,
                    37,
                    36,
                    28,
                    24,
                    29,
                    39,
                    47,
                    47,
                    39,
                    27,
                    0,
                    0,
                    0
                ]
            },
            {
                "name": "Saturday",
                "data": [
                    0,
                    0,
                    0,
                    0,
                    0,
                    0,
                    0,
                    13,
                    26,
                    41,
                    52,
                    55,
                    51,
                    45,
                    39,
                    33,
                    24,
                    0,
                    0,
                    0,
                    0,
                    0,
                    0,
                    0
                ]
            },
            {
                "name": "Sunday",
                "data": [
                    0,
                    0,
                    0,
                    0,
                    0,
                    0,
                    0,
                    0,
                    12,
                    25,
                    36,
                    39,
                    33,
                    27,
                    23,
                    18,
                    11,
                    0,
                    0,
                    0,
                    0,
                    0,
                    0,
                    0
                ]
            }
        ]
    },
    {
        "id": "ChIJ-0NIp5GaP44RFENhomoLV0w",
        "name": "Kinetics Functional Training",
        "address": "Cra. 11 #94-25, Bogot\u00e1, Cundinamarca, Colombia",
        "types": [
            "gym",
            "health",
            "point_of_interest",
            "establishment"
        ],
        "coordinates": {
            "lat": 4.678412,
            "lng": -74.04576300000001
        },
        "international_phone_number": "+57 601 6365059"
    },
    {
        "id": "ChIJL_QHhkGaP44RR8lEeBxBH7E",
        "name": "Gimnasio Spinnig Center",
        "address": "Cl. 69 #5, Bogot\u00e1, Colombia",
        "types": [
            "gym",
            "health",
            "point_of_interest",
            "establishment"
        ],
        "coordinates": {
            "lat": 4.650968,
            "lng": -74.055757
        },
        "rating": 4,
        "rating_n": 2
    },
    {
        "id": "ChIJ29sXwbuaP44RpLiR2RqrWXA",
        "name": "Gimnasio",
        "address": "Cl. 108 #17-65, Bogot\u00e1, Colombia",
        "types": [
            "gym",
            "health",
            "point_of_interest",
            "establishment"
        ],
        "coordinates": {
            "lat": 4.6930434,
            "lng": -74.0480728
        }
    },
    {
        "id": "ChIJs0t_ZEGaP44R5EfEdr3XcMc",
        "name": "Reebok Crossfit Zone G",
        "address": "Cl. 66 Bis ##4-36, Bogot\u00e1, Cundinamarca, Colombia",
        "types": [
            "gym",
            "health",
            "point_of_interest",
            "establishment"
        ],
        "coordinates": {
            "lat": 4.6488893,
            "lng": -74.0560629
        },
        "rating": 4.7,
        "rating_n": 34,
        "international_phone_number": "+57 350 5170799",
        "populartimes": [
            {
                "name": "Monday",
                "data": [
                    0,
                    0,
                    0,
                    0,
                    0,
                    16,
                    21,
                    21,
                    17,
                    11,
                    5,
                    8,
                    25,
                    32,
                    16,
                    12,
                    35,
                    71,
                    92,
                    79,
                    0,
                    0,
                    0,
                    0
                ]
            },
            {
                "name": "Tuesday",
                "data": [
                    0,
                    0,
                    0,
                    0,
                    0,
                    23,
                    44,
                    53,
                    43,
                    27,
                    20,
                    30,
                    44,
                    45,
                    36,
                    35,
                    48,
                    62,
                    67,
                    58,
                    0,
                    0,
                    0,
                    0
                ]
            },
            {
                "name": "Wednesday",
                "data": [
                    0,
                    0,
                    0,
                    0,
                    0,
                    15,
                    24,
                    27,
                    23,
                    15,
                    17,
                    46,
                    80,
                    63,
                    21,
                    18,
                    50,
                    86,
                    100,
                    78,
                    0,
                    0,
                    0,
                    0
                ]
            },
            {
                "name": "Thursday",
                "data": [
                    0,
                    0,
                    0,
                    0,
                    0,
                    22,
                    36,
                    39,
                    28,
                    13,
                    8,
                    29,
                    52,
                    44,
                    26,
                    28,
                    42,
                    56,
                    58,
                    50,
                    0,
                    0,
                    0,
                    0
                ]
            },
            {
                "name": "Friday",
                "data": [
                    0,
                    0,
                    0,
                    0,
                    0,
                    14,
                    48,
                    67,
                    51,
                    20,
                    4,
                    20,
                    39,
                    30,
                    26,
                    35,
                    45,
                    52,
                    53,
                    48,
                    0,
                    0,
                    0,
                    0
                ]
            },
            {
                "name": "Saturday",
                "data": [
                    0,
                    0,
                    0,
                    0,
                    0,
                    0,
                    0,
                    0,
                    0,
                    61,
                    76,
                    79,
                    71,
                    0,
                    0,
                    0,
                    0,
                    0,
                    0,
                    0,
                    0,
                    0,
                    0,
                    0
                ]
            },
            {
                "name": "Sunday",
                "data": [
                    0,
                    0,
                    0,
                    0,
                    0,
                    0,
                    0,
                    0,
                    0,
                    0,
                    14,
                    21,
                    0,
                    0,
                    0,
                    0,
                    0,
                    0,
                    0,
                    0,
                    0,
                    0,
                    0,
                    0
                ]
            }
        ]
    }
]